pyArchiver/__init__.py
pyArchiver/pyArchiver.py
tests/__init__.py
tests/test_archiver.py
pyArchiverVadim-2.0.0.dist-info/METADATA
pyArchiverVadim-2.0.0.dist-info/WHEEL
pyArchiverVadim-2.0.0.dist-info/top_level.txt
pyArchiverVadim-2.0.0.dist-info/RECORD
