Metadata-Version: 2.1
Name: pyArchiverVadim
Version: 2.0.0
Summary: Archiver
Home-page: https://github.com/veeeedro/pyArchiver
Author: Silenov V.O.
Author-email: veeeedro@mail.ru
License: UNKNOWN
Platform: any
Requires-Python: >=3.7
